kaspy/__init__.py
kaspy/defines.py
kaspy/kaspa_clients.py
kaspy/streams.py
kaspy/excepts/__init__.py
kaspy/excepts/exceptions.py
kaspy/log_handler/__init__.py
kaspy/log_handler/log_messages.py
kaspy/network/__init__.py
kaspy/network/node.py
kaspy/protos/__init__.py
kaspy/protos/messages_pb2.py
kaspy/protos/messages_pb2_grpc.py
kaspy/protos/p2p_pb2.py
kaspy/protos/rpc_pb2.py
kaspy/utils/__init__.py
kaspy/utils/version_comparer.py
kaspy-0.0.13.dist-info/LICENCE
kaspy-0.0.13.dist-info/METADATA
kaspy-0.0.13.dist-info/WHEEL
kaspy-0.0.13.dist-info/top_level.txt
kaspy-0.0.13.dist-info/RECORD
