Metadata-Version: 2.1
Name: kaspy
Version: 0.0.13
Summary: Python implementation of a kaspa grpc client
Home-page: https://github.com/kaspagang/kaspy
Author: D-Stacks
License: GPL-3.0 License
Classifier: Programming Language :: Python :: 3
Requires-Python: >=3.8
License-File: LICENCE
Requires-Dist: requests
Requires-Dist: grpcio
Requires-Dist: grpcio-tools
Requires-Dist: sockets
